README.md
setup.py
randomizer/__init__.py
randomizer/partial.py
randomizer/randomize.py
randomizer.egg-info/PKG-INFO
randomizer.egg-info/SOURCES.txt
randomizer.egg-info/dependency_links.txt
randomizer.egg-info/top_level.txt