Metadata-Version: 2.1
Name: randomizer
Version: 0.21
Summary: Liberty for generate random data.
Home-page: https://github.com/Saylermb/randomizer
Author: Saylermb
Author-email: Saylermb@gmail.com
License: The MIT License: http://www.opensource.org/licenses/mit-license.php
Platform: UNKNOWN
Classifier: Development Status :: 3 - Alpha
Classifier: Intended Audience :: Developers
Classifier: Intended Audience :: Developers
Classifier: License :: OSI Approved :: MIT License
Classifier: Natural Language :: English
Classifier: Topic :: Software Development :: Libraries :: Python Modules
Classifier: Topic :: Education :: Testing
Classifier: Topic :: Text Processing
Classifier: Topic :: Utilities
Requires-Python: >3.6.2
